aiohttp_pydantic/__init__.py
aiohttp_pydantic/decorator.py
aiohttp_pydantic/injectors.py
aiohttp_pydantic/uploaded_file.py
aiohttp_pydantic/utils.py
aiohttp_pydantic/view.py
aiohttp_pydantic/oas/__init__.py
aiohttp_pydantic/oas/__main__.py
aiohttp_pydantic/oas/cmd.py
aiohttp_pydantic/oas/definition.py
aiohttp_pydantic/oas/docstring_parser.py
aiohttp_pydantic/oas/index.j2
aiohttp_pydantic/oas/struct.py
aiohttp_pydantic/oas/typing.py
aiohttp_pydantic/oas/view.py
aiohttp_pydantic-2.5.2.dist-info/licenses/LICENSE
aiohttp_pydantic-2.5.2.dist-info/METADATA
aiohttp_pydantic-2.5.2.dist-info/WHEEL
aiohttp_pydantic-2.5.2.dist-info/top_level.txt
aiohttp_pydantic-2.5.2.dist-info/RECORD
