Metadata-Version: 2.4
Name: aiohttp_pydantic
Version: 2.5.2
Summary: Aiohttp View using pydantic to validate request body and query sting regarding method annotations.
Home-page: https://github.com/Maillol/aiohttp-pydantic
Author: Vincent Maillol
Author-email: vincent.maillol@gmail.com
License: MIT
Keywords: aiohttp,pydantic,annotations,validation
Classifier: Intended Audience :: Developers
Classifier: Intended Audience :: Information Technology
Classifier: Programming Language :: Python
Classifier: Programming Language :: Python :: 3
Classifier: Programming Language :: Python :: 3 :: Only
Classifier: Programming Language :: Python :: 3.8
Classifier: Programming Language :: Python :: 3.9
Classifier: Programming Language :: Python :: 3.10
Classifier: Programming Language :: Python :: 3.11
Classifier: Programming Language :: Python :: 3.12
Classifier: Programming Language :: Python :: 3.13
Classifier: Topic :: Software Development :: Libraries :: Application Frameworks
Classifier: Framework :: aiohttp
Requires-Python: >=3.8
License-File: LICENSE
Requires-Dist: aiohttp
Requires-Dist: jinja2
Requires-Dist: packaging
Requires-Dist: pydantic<3.0,>=2.0
Requires-Dist: typing-extensions
Provides-Extra: test
Requires-Dist: pytest==7.2.0; extra == "test"
Requires-Dist: pytest-aiohttp==1.0.5; extra == "test"
Requires-Dist: pytest-cov==4.0.0; extra == "test"
Requires-Dist: readme-renderer==37.3; extra == "test"
Requires-Dist: build>=1.0.3; extra == "test"
Provides-Extra: ci
Requires-Dist: pytest==7.2.0; extra == "ci"
Requires-Dist: pytest-aiohttp==1.0.5; extra == "ci"
Requires-Dist: pytest-cov==4.0.0; extra == "ci"
Requires-Dist: readme-renderer==37.3; extra == "ci"
Requires-Dist: build>=1.0.3; extra == "ci"
Requires-Dist: codecov==2.1.13; extra == "ci"
Requires-Dist: twine<7,>=6; extra == "ci"
Dynamic: license-file
